{
  "name": "Dan Carrier",
  "type": "Legendary Creature — Human Shaman",
  "team": "truffle_hogs",
  "handicap": "21",
  "artPosition": "50% 42%",
  "abilities": [
    "<span class='win trophy'>★ Hair of the Hog</span> — passes the flask down the Truffle Hog line before every round; a nose beer, he swears, knocks strokes clean off. Handicaps drop at the first tee.",
    "<span class='yr'>Root &amp; Ruin.</span> The hog devours what the Syndicate grows — slip a Mycelian a gram and five strokes bloom on their card. 2025 <span class='win'>Pairs Champion</span> with Jordo (the Double-D); handicap rooted down 30 → 26 → 21."
  ],
  "flavor": "“Mushrooms add five strokes a gram; nose beers bring it right back down. I'm just balancing the books.”",
  "collector": "023/021",
  "rarity": "M",
  "caption": "Dan Carrier · Truffle Hogs 🐗"
}
